calculadora_IMC/__init__.py
calculadora_IMC/imc.py
calculadora_IMC-0.0.1.dist-info/METADATA
calculadora_IMC-0.0.1.dist-info/WHEEL
calculadora_IMC-0.0.1.dist-info/top_level.txt
calculadora_IMC-0.0.1.dist-info/RECORD
