Metadata-Version: 2.1
Name: calculadora-IMC
Version: 0.0.1
Summary: Calculadora de IMC simples
Home-page: https://github.com/Hanieri21/Hanieri21/tree/imc/Calculadora%20IMC
Author: Ytalo Hanieri Brito
Author-email: hanieri21@gmail.com
License: UNKNOWN
Platform: UNKNOWN
Requires-Python: >=3.8
